Tareas/Tarea_Digitales2/probador_Mux.v
module probador_Mux(
	output reg		clok,
	input		[1:0] data_out,
	output reg	reset_L,
	output reg	selector,
	output reg	[1:0] data_in0,
	output reg	[1:0] data_in1);
	
	initial begin
		$dumpfile("Mux.vcd");
		$dumpvars;
		$display ("\t\t\tclok,\tsMux_cond,\treset_L, \tselector,\tdata_in0,\tdata_in1");
		$monitor($time,"\t%b\t%b\t\t%b\t\t%b\t%b\t%b", clok, data_out, reset_L, selector, data_in0, data_in1);
		
		// Valores iniciales de las señales.
		reset_L = 'b0;             
		selector = 'b0;            
		data_in0[0] = 0;
		data_in0[1] = 0;
		data_in1 = 0;
		/*Se especifica linia por linia el comportamiento de la señal para imitar
		el comportamiento de las señales que aparecen en la propuesta del profesor,
		y como no se tiene mucho conocimiento de verilog, el codigo esta poco obtimizado.*/
		#10 reset_L = 1; 
		
		#4 data_in0 = ~data_in0;
		data_in1[0] = data_in1[0];
		data_in1[1] = ~data_in1[1];
		
		
		#4 selector = ~selector;
		data_in0[0] = data_in0[0];
		data_in0[1] = ~data_in0[1];
		data_in1[0] = data_in1[0];
		data_in1[1] = ~data_in1[1];
		
		#4 data_in0[0] = ~data_in0[0];
		data_in0[1] = data_in0[1];
		data_in1[0] = data_in1[0];
		data_in1[1] = ~data_in1[1];
		
		#4 selector = ~selector;
		data_in0[0] = ~data_in0[0];
		data_in0[1] = ~data_in0[1];
		data_in1[0] = ~data_in1[0];
		data_in1[1] = data_in1[1];
		
		#4 selector = ~selector;
		data_in0 = ~data_in0;
		data_in1[0] = data_in1[0];
		data_in1[1] = ~data_in1[1];
		
		#4 selector = ~selector;
		$finish;
		
	end
	// Reloj
	initial	clok 	<= 0;			// Valor inicial al reloj, sino siempre será indeterminado
	always	#2 clok 	<= ~clok;		// Hace "toggle" cada 4 segundos
endmodule

Tareas/Tarea_Digitales2/Mux_Conductual.v
module Mux_Conductual (
	output reg	[1:0] data_out,
	input 		clok,
	input 		reset_L,	
	input 		selector,
	input 		[1:0] data_in0,
	input 		[1:0] data_in1);
	reg	[1:0] salida1;            //Variable auxiliar, utìl para el funcionamiento interno del mòdulo.

	always @ (*) begin
		
		if (selector == 1 )
			salida1 = data_in1;	// Asignación bloqueante por ser cobinacional
      		else
			salida1 = data_in0;	
    	end


	always @ (posedge clok) begin           //<<   >>
	
		if (reset_L==1)
		
			data_out <= salida1; // Asignación no bloqueante por ser secuencial.
		else
			data_out <= 'b0;
	end
endmodule

Tareas/Tarea_Digitales2/BancoPrueba_Mux.v
`timescale 	1s				/ 100ps
// escala	unidad temporal (valor de "#4") / precisión
// Pueden omitirse y llamarse desde el testbench
`include "Mux_Conductual.v"
`include "probador_Mux.v"

module BancoPrueba_Mux; // Testbench
	//Los buses se deben declarar en lineas aparte por ser de diferentes tamaños.
	wire [1:0] data_out;
	wire reset_L, selector;  
	wire [1:0] data_in0; 
	wire [1:0] data_in1;

	// Descripción conductual de alarma, las instancias se realizan por medio de AUTOINST.
	Mux_Conductual	Mux_Intanciado_cond( /*AUTOINST*/
					    // Outputs
					    .data_out		(data_out[1:0]),
					    // Inputs
					    .clok		(clok),
					    .reset_L		(reset_L),
					    .selector		(selector),
					    .data_in0		(data_in0[1:0]),
					    .data_in1		(data_in1[1:0]));
	
	// Probador: generador de señales y monitor
	probador_Mux probador_Instanciado( /*AUTOINST*/
					  // Outputs
					  .clok			(clok),
					  .reset_L		(reset_L),
					  .selector		(selector),
					  .data_in0		(data_in0[1:0]),
					  .data_in1		(data_in1[1:0]),
					  // Inputs
					  .data_out		(data_out[1:0]));
endmodule

Tareas/Tarea_Digitales2/Mux.vcd
$date
	Mon Aug 31 00:15:26 2020
$end
$version
	Icarus Verilog
$end
$timescale
	100ns
$end
$scope module BancoPrueba_Mux $end
$var wire 1 ! selector $end
$var wire 1 " reset_L $end
$var wire 2 # data_out [1:0] $end
$var wire 2 $ data_in1 [1:0] $end
$var wire 2 % data_in0 [1:0] $end
$var wire 1 & clok $end
$scope module Mux_Intanciado_cond $end
$var wire 1 ! selector $end
$var wire 1 " reset_L $end
$var wire 2 ' data_in1 [1:0] $end
$var wire 2 ( data_in0 [1:0] $end
$var wire 1 & clok $end
$var reg 2 ) data_out [1:0] $end
$var reg 2 * salida1 [1:0] $end
$upscope $end
$scope module probador_Instanciado $end
$var wire 2 + data_out [1:0] $end
$var reg 1 & clok $end
$var reg 2 , data_in0 [1:0] $end
$var reg 2 - data_in1 [1:0] $end
$var reg 1 " reset_L $end
$var reg 1 ! selector $end
$upscope $end
$upscope $end
$enddefinitions $end
#0
$dumpvars
b0 -
b0 ,
bx +
b0 *
bx )
b0 (
b0 '
0&
b0 %
b0 $
bx #
0"
0!
$end
#20000
b0 #
b0 )
b0 +
1&
#40000
0&
#60000
1&
#80000
0&
#100000
1&
1"
#120000
0&
#140000
b11 #
b11 )
b11 +
1&
b11 *
b10 $
b10 '
b10 -
b11 %
b11 (
b11 ,
#160000
0&
#180000
b0 #
b0 )
b0 +
1&
b0 *
b0 $
b0 '
b0 -
b1 %
b1 (
b1 ,
1!
#200000
0&
#220000
b10 #
b10 )
b10 +
1&
b10 *
b10 $
b10 '
b10 -
b0 %
b0 (
b0 ,
#240000
0&
#260000
b11 #
b11 )
b11 +
1&
b11 *
b11 $
b11 '
b11 -
b11 %
b11 (
b11 ,
0!
#280000
0&
#300000
b1 #
b1 )
b1 +
1&
b1 *
b1 $
b1 '
b1 -
b0 %
b0 (
b0 ,
1!
#320000
0&
#340000
b0 #
b0 )
b0 +
1&
b0 *
0!
